{
  "page_content": "### **Email Template: Dr. Fateme Esmailie**\n*(The Personable & Collaborative Professor)*  \nSubject: A Quick Request for a Letter of Recommendation \u2013 [Your Name]  \nHi Dr. Esmailie,  \nI hope you're having a wonderful week! I wanted to reach out again regarding my graduate school application in CS/AI and potential professional references (Technical Solutions Engineer). As we discussed before, I'm now looking to strengthen this part of my portfolio with your support.  \nYour willingness to collaborate on the letter draft was so appreciated\u2014especially when you shared about your cats and family! It made me feel like a real student in your class. Since then, I\u2019ve completed [briefly mention key achievement: e.g., \"a research project on AI-driven diagnostics\" or \"my capstone in machine learning\"], which I believe would be valuable to include in the letter.  \nWould you be open to reviewing a draft version that I\u2019ll share with you? If so, please let me know what format works best for you (e.g., Word doc or Google Doc), and if there\u2019s anything specific about my work you\u2019d like me to highlight. I\u2019m happy to adjust any details to make this as smooth as possible for your schedule.  \nLooking forward to hearing from you!  \nBest,\n[Your Full Name]\n[Student ID/Program, if applicable]\n[Contact Information]  \n---",
  "metadata": {
    "Subsection": "**Email Template: Dr. Fateme Esmailie**",
    "source_file": "LORS\\LOR Templates.md",
    "parent_index": 2,
    "file_hash": "8b7ecd0d172a0b448b5de88733c7e686007e41fe191973a224195ff028c963ca"
  }
}