{
  "page_content": "### Question 57\n- **Question:** When studying education as a social institution, the hidden curriculum constitutes:\n- **Subject:** Sociology\n- **Skill:** #Scientific_Reasoning_and_Problem_Solving2\n- **Content Category:** #CC_9A_Understanding_social_structure\n- **Subtopic/Error Type:** #UnknownDefintion\n- **My Answer:** a discriminatory function of schools.\n- **Correct Answer:** a latent function of schools.\n- **AAMC Reasoning:**\n- Based on my answer choice: Discrimination is the unfair treatment of an individual due to their social background. This is not consistent with the definition of the hidden curriculum.\n- Correct answer choice: A latent function is an unintended positive outcome of a social practice. Hidden curriculum refers to the unintended positive consequences of learning experiences in educational institutions, such as learning how to behave in a formal setting and cooperation among peers. Therefore, the hidden curriculum is best described as a latent function of education.\n- **Personal Reasoning:**  \n---",
  "metadata": {
    "Subsection": "Question 57",
    "tags": [
      "CC_8A_Self_identity",
      "CC_8C_Social_interactions",
      "CC_9A_Understanding_social_structure",
      "CC_9B_Demographic_characteristics_and_processes",
      "ConceptualMisunderstanding",
      "Data_Based_Statistical_Reasoning4",
      "GraphicalInterpretation",
      "Knowledge_of_Scientific_Principles1",
      "ScientificContent",
      "Scientific_Reasoning_and_Problem_Solving2",
      "UnknownDefintion"
    ],
    "source_file": "Psychology_Sociology\\PE3_Misc_1.md",
    "parent_index": 3,
    "file_hash": "bdb465c344907a2423d16e7affb60055baca72e814c3efdef7aebbcdeb6676cd"
  }
}