{
  "page_content": "### Question\n- **Skill:** #Reasoning_Beyond_the_Text\n- **Error_Type:** #AuthorsEvidence\n- **Question:** Paste the question here\n- **My Answer:** crevecoeur\n- **Correct Answer:** de Tocqueville\n- **AAMC Reasoning:**\n- Based on my answer choice: The author comments that Cr\u00e8vecoeur failed to see that the purely economic person was unsuited for a self-governing society. See rationale B.\n- Correct answer choice: In commenting about how Cr\u00e8vecoeur failed to see \u201cthat a purely economic person would be as unsuited to a self-governing society as would the rank-bound subject of traditional regimes\u201d, the author suggests that de Tocqueville \u201cgave a much more adequate view\u201d. The author later specifies how de Tocqueville viewed the purely economic man by commenting that de Tocqueville \u201cappreciated the commercial and entrepreneurial spirit [in the U.S.] . . . but saw it as having ambiguous and problematic implications for the future of American freedom\u201d.  \n---  \n### Question\n- **Skill:** #Foundations_of_Comprehension\n- **Error_Type:** #AvoidanceOfSensitiveTopic (oftentimes if the question has a keyword about a sensitive topic I think the AAMC wants students to not answer using the responses that we are most biased towards giving i.e. the political, or religious one)\n- **Question:** The passage suggests that de Tocqueville\u2019s analysis of America might have been more accurate than Cr\u00e8vecoeur\u2019s because de Tocqueville possessed:\n- **My Answer:** a bias in favor of rational self-interest.\n- **Correct Answer:** a belief in republican principles.\n- **AAMC Reasoning:**\n- Based on my answer choice: The author indicates that Cr\u00e8vecoeur, more than de Tocqueville, championed the rational self-interest that informed the \u201cEconomic Being\u201d. De Tocqueville found the purely economic person as \u201chaving ambiguous and problematic implications for the future of American freedom\u201d.\n- Correct answer choice: De Tocqueville\u2019s belief in republican principles is underscored by the author\u2019s discussion of how mores, more than even laws or physical circumstances, contributed to maintaining the American democratic republic. The author further maintains that this is a fuller, more \u201cadequate view\u201d than Cr\u00e8vecoeur\u2019s: \u201c[De Tocqueville] added to Cr\u00e8vecoeur\u2019s earlier sketch a more penetrating and complex understanding of the new society, informed by republican convictions and a deep sensitivity to the place of religion in human life\u201d.  \n---  \n### Question\n- **Skill:** #Foundations_of_Comprehension\n- **Error_Type:** #TextualEvidence\n- **Question:**\n- According to the passage, the optimism of French Enlightenment scholars was called into question by:\n- the economic development of Americans.\n- the French Revolution and its aftermath.\n- conditions in English mill towns.\n- **My Answer:** I and II only\n- **Correct Answer:** II and III only\n- **AAMC Reasoning:**\n- Based on my answer choice:The author does not cite economic development in the U.S. as a factor. For Cr\u00e8vecoeur, American economic development confirmed enlightenment optimism: \u201cThe rational, self-interested individual had emerged as Economic Being and, as such, was conceived as living most naturally in the conditions of a competitive market in which trade and exchange would replace traditional ranks and loyalties as the coordinating mechanism of social life\u201d. Even de Tocqueville appreciated the entrepreneurial spirit in the U.S. even though he considered it problematic. However, the author does not cite the American entrepreneurial spirit in particular as leading de Tocqueville to question Enlightenment thinking\u2014it was English mill towns and the French Revolution that made him skeptical of Enlightenment optimism.\n- Correct answer choice: In discussing de Tocqueville\u2019s views, the author is explicit on this point: \u201cFor de Tocqueville, the optimism of the Enlightenment had been tempered by the experience of the French Revolution and its aftermath, and the prophecies of the early political economists were finding an alarmingly negative fulfillment in the industrial infernos of English mill towns\u201d.  \n---  \n### Question\n- **Skill:** #Reasoning_Within_the_Text\n- **Error_Type:** #Misread_Author_Tone\n- **Question:** On the basis of the passage, a comparison of Cr\u00e8vecoeur\u2019s and de Tocqueville\u2019s views of America might reasonably lead to the conclusion that:\n- **My Answer:** both Cr\u00e8vecoeur and de Tocqueville were extremely optimistic about America\u2019s future.\n- **Correct Answer:** de Tocqueville was somewhat more pessimistic than Cr\u00e8vecoeur about America\u2019s future.\n- **AAMC Reasoning:**\n- Based on my answer choice: Only de Cr\u00e8vecoeur demonstrated extreme optimism. See rationale B.\n- Correct answer choice: Cr\u00e8vecoeur based his optimism on the entrepreneurial spirit and self-made, self-reliant qualities of the American \u201cEconomic Being,\u201d which the author calls \u201can emancipated, enlightened individual confidently directing energies toward the environment, both natural and social, aiming to wring from it a comfortable happiness\u201d. However, the author points out that Cr\u00e8vecoeur could not see what many Americans of his time saw, namely, \u201cthat a purely economic person would be unsuited to a self-governing society. . . .\u201d De Tocqueville found reason for pessimism where Cr\u00e8vecoeur found reason for optimism: \u201c[De Tocqueville] appreciated the commercial and entrepreneurial spirit that Cr\u00e8vecoeur had emphasized but saw it as having ambiguous and problematic implications for the future of American freedom\u201d.  \n---",
  "metadata": {
    "Document Title": "Passage:",
    "Subsection": "Question",
    "tags": [
      "AuthorsEvidence",
      "AvoidanceOfSensitiveTopic",
      "Foundations_of_Comprehension",
      "Misread_Author_Tone",
      "Reasoning_Beyond_the_Text",
      "Reasoning_Within_the_Text",
      "TextualEvidence"
    ],
    "source_file": "CARS\\American Character.md",
    "parent_index": 2,
    "file_hash": "35afd8278ef7364972e50c99f9efaf066eaba45a73449910ef3b24c1e8a0e603"
  }
}