{
  "page_content": "# Passage:\nIodine and zinc are the reactants in an experiment to find the stoichiometry of a reaction. Gray, granular zinc metal (2.0 g) and purple iodine crystals (2.0 g) are added to an Erlenmeyer flask containing 25 mL of methanol (CH3OH). The iodine dissolves in the methanol giving a red-brown solution. After 15 min of heating, the solution is pale yellow, and a few gray granules remain at the bottom of the flask. The liquid is decanted into a beaker. The remaining granules are rinsed several times with methanol, and the methanol from each rinse is added to the beaker. The methanol is then evaporated, leaving a solid, yellow-white product of iodide of zinc. The mass of the dry product is obtained. The unreacted zinc granules are also dried and weighed.  \nA 2:1 ratio of moles of iodine atoms to zinc atoms in the product is consistently obtained. The mass of iodine and reacted zinc equals the mass of product.  \nThe standard reduction potentials for zinc, iodine, and two other substances are given in Table 1.  \nTable 1Standard Reduction Potentials at 25\u00b0C  \n|   |   |   |   |   |\n|---|---|---|---|---|\n|Oxidizing agent|Electrons gained||Reducing agent|_E_\u00b0(V)|\n|I2|+2e\u2013|\u2192|2I\u2013|+0.54|\n|Sn2+|+2e\u2013|\u2192|Sn|\u20130.14|\n|Fe2+|+2e\u2013|\u2192|Fe|\u20130.44|\n|Zn2+|+2e\u2013|\u2192|Zn|\u20130.76|  \nThe limiting reagent in the experiments described in the passage is:  \n---",
  "metadata": {
    "Document Title": "Passage:",
    "tags": [
      "CC_4E_Atoms_nuclear_decay_electronic_structure_and_atomic_chemical_behavior",
      "Knowledge_of_Scientific_Principles1",
      "Scientific_Reasoning_and_Problem_Solving2"
    ],
    "source_file": "Physics_Chem\\PE3_Phys_P3.md",
    "parent_index": 1,
    "file_hash": "bc87ce7c87ff82b9cb18ea24b971dcbc18995d10c9c2827d9de1920ba5a026b6"
  }
}