{
  "page_content": "# Passage:\nAs citizens of the cosmo polis, the mythical \u201cworld city,\u201d professors are expected to owe no allegiance to geographical territory; they\u2019re supposed to belong to the boundless world of books, ideas, and eternal truths, not the infinitely particular world of watersheds, growing seasons, and ecological niches. Most professors get their jobs through national searches, and although they may have geographical preferences, most are living wherever they can find work.  \nThough the majority of U.S. college students attend institutions in their home states, they are taught by this cosmopolitan class of transient exotics. It would be surprising if the rootlessness of the professorial class did not affect their students who go on to become the best-informed, most-educated portion of the U.S. public. Education certainly ought to broaden horizons, but it can and ought to do more. However we define that more, one thing seems clear: rootless professors are systematically ignorant of a key aspect of integrated life, the life that is, after all, a primary goal of a good liberal arts education. They are ignorant of the values of connectedness to place.  \nThis ignorance gives preference to the voice of the abstract at the expense of the voice of the particular. This can only be done by dismissing out of hand the possibility that because moral questions come to us not in the abstract but as concrete, particular problems, solutions to moral questions will necessarily be particular and specific. If we cannot get rid of the causes of this problem, we can alleviate the symptoms. This may be the better course, for it presents the opportunity to keep what is good in both cosmopolitanism and provincialism.  \nFirst, academia has to overcome its prejudice against the local and the provincial, so that its hiring committees do not include non-native status as an implicit qualification for employment. Such prejudice is dramatized in the case of one individual who, having received his degrees from the university in his home state and having worked at that institution as a lecturer on temporary contract, was told by the department chair that he was \u201ctoo much a native\u201d ever to become a permanent faculty member.  \nSecond, professors should include local content in their courses. Not abstract theories about distant peoples, but concrete realizations about observable communities; not airy generalizations that transcend student experience and lie beyond their powers of criticism, but specific conclusions whose skeptical testing they can perform themselves; not social-science hearsay taken on faith, but evidence weighed critically, firsthand: these form the substance of a rooted education. Transforming the world immediately outside the classroom into a laboratory will tend to erase the artificial boundary between the roles of student and citizen, thereby encouraging the latter in the habits of the former.  \nFinally, academics ought to work to acquire a kind of dual citizenship\u2014in the world of ideals and scholarship, yes, but also in the very real world of watersheds, growing seasons, migratory pathways, food chains, and dependency webs. What is needed is a class of cosmopolitan educators willing to live where they work and to work where they live, a class of educators willing to take root and cultivate a sense of place. These educators could then exemplify in their teaching and in their lives their own manner of accommodation to the fruitful tension between local and universal, particular and general, concrete and abstract. In an age when humanity\u2019s relationship to nature is so in need of careful, farsighted attention, academics do a disservice to their students, and to the future of human culture on the planet, if they do anything less.  \n---",
  "metadata": {
    "Document Title": "Passage:",
    "tags": [
      "AuthorsAssumptions",
      "AuthorsImplications",
      "Foundations_of_Comprehension"
    ],
    "source_file": "CARS\\Professors.md",
    "parent_index": 0,
    "file_hash": "f15093d74a66575b54d74bcac1273cc47d6953ee94d466c94b57e3bf43f6c4be"
  }
}